ncopa/__init__.py
ncopa/comment.py
ncopa/find.py
ncopa/parse.py
ncopa/search.py
ncopa/traverse.py
ncopa/tree.py
ncopa-0.2.0.dist-info/METADATA
ncopa-0.2.0.dist-info/WHEEL
ncopa-0.2.0.dist-info/entry_points.txt
ncopa-0.2.0.dist-info/licenses/LICENSE
ncopa-0.2.0.dist-info/RECORD
