Metadata-Version: 2.4
Name: ncopa
Version: 0.2.0
Summary: ncopa: nginx.conf parser
Author-email: Hai Vu <haivu2004@gmail.com>
License-File: LICENSE
Requires-Python: >=3.12
